juju_doctor/__init__.py
juju_doctor/artifacts.py
juju_doctor/constants.py
juju_doctor/fetcher.py
juju_doctor/helpers.py
juju_doctor/main.py
juju_doctor/probes.py
juju_doctor/results.py
juju_doctor/tree.py
juju_doctor/builtin/app-relation-exists.py
juju_doctor/builtin/application-exists.py
juju_doctor/builtin/offer-exists.py
juju_doctor-0.1.8.dist-info/METADATA
juju_doctor-0.1.8.dist-info/WHEEL
juju_doctor-0.1.8.dist-info/entry_points.txt
juju_doctor-0.1.8.dist-info/licenses/LICENSE
juju_doctor-0.1.8.dist-info/RECORD
