Metadata-Version: 2.4
Name: juju-doctor
Version: 0.1.8
Summary: Juju-doctor is a pypi package which helps validate Juju deployments using probes.
Project-URL: Homepage, https://github.com/canonical/juju-doctor
Project-URL: PyPI, https://pypi.org/project/juju-doctor
License: 
License-File: LICENSE
Requires-Python: >=3.10
Requires-Dist: fsspec
Requires-Dist: pydantic
Requires-Dist: pyyaml
Requires-Dist: requests
Requires-Dist: sh
Requires-Dist: treelib
Requires-Dist: typer
Provides-Extra: dev
Requires-Dist: coverage[toml]; extra == 'dev'
Requires-Dist: pyright; extra == 'dev'
Requires-Dist: pytest; extra == 'dev'
Requires-Dist: ruff; extra == 'dev'
Provides-Extra: doctest
Requires-Dist: pyyaml; extra == 'doctest'
Requires-Dist: rich; extra == 'doctest'
